decent_dp/__init__.py
decent_dp/ddp.py
decent_dp/topo.py
decent_dp/utils.py
decent_dp-0.6.1.dist-info/LICENSE
decent_dp-0.6.1.dist-info/METADATA
decent_dp-0.6.1.dist-info/WHEEL
decent_dp-0.6.1.dist-info/top_level.txt
decent_dp-0.6.1.dist-info/RECORD
