Metadata-Version: 2.1
Name: decent-dp
Version: 0.6.1
Summary: An implementation of decentralized data parallel based on PyTorch
Author-email: Zesen Wang <zesen@kth.se>
License: MIT License
Project-URL: Homepage, https://github.com/WangZesen/decentralized-data-parallel
Project-URL: Issues, https://github.com/WangZesen/decentralized-data-parallel/issues
Classifier: Programming Language :: Python :: 3
Classifier: License :: OSI Approved :: MIT License
Classifier: Operating System :: OS Independent
Requires-Python: >=3.11
License-File: LICENSE
Requires-Dist: torch >=2.1.0
Requires-Dist: loguru >=0.7.0
Provides-Extra: test
Requires-Dist: tqdm >=4.66.0 ; extra == 'test'
